setup.py
pycc/__init__.py
pycc/loader.py
pycc/module.py
pycc.egg-info/PKG-INFO
pycc.egg-info/SOURCES.txt
pycc.egg-info/dependency_links.txt
pycc.egg-info/entry_points.txt
pycc.egg-info/top_level.txt
pycc/asttools/__init__.py
pycc/asttools/references.py
pycc/cli/__init__.py
pycc/cli/args.py
pycc/cli/common.py
pycc/cli/compile.py
pycc/cli/transform.py
pycc/optimizers/__init__.py
pycc/optimizers/base.py
pycc/optimizers/constant.py