Metadata-Version: 1.1
Name: pycc
Version: 1.0.0
Summary: Python code optimizer.
Home-page: https://github.com/kevinconway/pycc
Author: Kevin Conway
Author-email: kevinjacobconway@gmail.com
License: 
